shapelets/__init__.py
shapelets/__main__.py
shapelets/_api.py
shapelets/_cli.py
shapelets/_relations.py
shapelets/_uom.py
shapelets/_version.py
shapelets/_version.pyi
shapelets/functions.py
shapelets/iris.csv
shapelets/py.typed
shapelets/systemd_template.txt
shapelets/apps/__init__.py
shapelets/apps/data_app.py
shapelets/apps/data_app_utils.py
shapelets/apps/widgets/__init__.py
shapelets/apps/widgets/attribute_names.py
shapelets/apps/widgets/util.py
shapelets/apps/widgets/widget.py
shapelets/apps/widgets/charts/__init__.py
shapelets/apps/widgets/charts/altair_chart.py
shapelets/apps/widgets/charts/bar_chart.py
shapelets/apps/widgets/charts/folium_chart.py
shapelets/apps/widgets/charts/heatmap.py
shapelets/apps/widgets/charts/histogram.py
shapelets/apps/widgets/charts/line_chart.py
shapelets/apps/widgets/charts/pie_chart.py
shapelets/apps/widgets/charts/plotly_chart.py
shapelets/apps/widgets/charts/polar_area.py
shapelets/apps/widgets/charts/radar_area.py
shapelets/apps/widgets/charts/scatter_plot.py
shapelets/apps/widgets/contexts/__init__.py
shapelets/apps/widgets/contexts/filtering_context.py
shapelets/apps/widgets/contexts/metadata_field.py
shapelets/apps/widgets/contexts/metadata_filter.py
shapelets/apps/widgets/contexts/temporal_context.py
shapelets/apps/widgets/controllers/__init__.py
shapelets/apps/widgets/controllers/button.py
shapelets/apps/widgets/controllers/checkbox.py
shapelets/apps/widgets/controllers/collection_selector.py
shapelets/apps/widgets/controllers/datetime_range_selector.py
shapelets/apps/widgets/controllers/datetime_selector.py
shapelets/apps/widgets/controllers/image.py
shapelets/apps/widgets/controllers/list.py
shapelets/apps/widgets/controllers/multi_sequence_selector.py
shapelets/apps/widgets/controllers/number_input.py
shapelets/apps/widgets/controllers/radio_group.py
shapelets/apps/widgets/controllers/selector.py
shapelets/apps/widgets/controllers/sequence_list.py
shapelets/apps/widgets/controllers/sequence_selector.py
shapelets_platform-2.0.53.dist-info/LICENSE.md
shapelets_platform-2.0.53.dist-info/METADATA
shapelets_platform-2.0.53.dist-info/WHEEL
shapelets_platform-2.0.53.dist-info/entry_points.txt
shapelets_platform-2.0.53.dist-info/top_level.txt
shapelets_platform-2.0.53.dist-info/RECORD
